README.md
dfm.py
setup.py
dotfilesmanager.egg-info/PKG-INFO
dotfilesmanager.egg-info/SOURCES.txt
dotfilesmanager.egg-info/dependency_links.txt
dotfilesmanager.egg-info/entry_points.txt
dotfilesmanager.egg-info/not-zip-safe
dotfilesmanager.egg-info/requires.txt
dotfilesmanager.egg-info/top_level.txt