Metadata-Version: 1.1
Name: dotfilesmanager
Version: 1.0.6
Summary: dotfiles管理工具
Home-page: https://github.com/xyz1001/dotfilesmanager
Author: xyz1001
Author-email: zgzf1001@gmail.com
License: MIT
Keywords: python dotfiles
Platform: UNKNOWN
Classifier: Programming Language :: Python :: 3
